buabuaml/__init__.py
buabuaml/errors.py
buabuaml/http.py
buabuaml/serialization.py
buabuaml/services.py
buabuaml-0.3.0.dev0.dist-info/DESCRIPTION.rst
buabuaml-0.3.0.dev0.dist-info/METADATA
buabuaml-0.3.0.dev0.dist-info/RECORD
buabuaml-0.3.0.dev0.dist-info/WHEEL
buabuaml-0.3.0.dev0.dist-info/metadata.json
buabuaml-0.3.0.dev0.dist-info/top_level.txt
