Metadata-Version: 2.0
Name: buabuaml
Version: 0.3.0.dev0
Summary: BuaBua Machine Learning Python client library
Home-page: https://h_kimu@bitbucket.org/datasciencelab/buabuaml-clientlib-python-dev.git
Author: DSL
Author-email: h.kimu@opt.ne.jp
License: MIT License
Platform: UNKNOWN
Classifier: Development Status :: 3 - Alpha
Classifier: Programming Language :: Python
Classifier: Programming Language :: Python :: 2
Classifier: Programming Language :: Python :: 2.7
Classifier: Programming Language :: Python :: 3
Classifier: Programming Language :: Python :: 3.3
Classifier: Programming Language :: Python :: 3.4
Classifier: License :: OSI Approved :: MIT License
Requires-Dist: pandas
Requires-Dist: python-dateutil
Requires-Dist: requests
